libreria_experimental/__init__.py
libreria_experimental/_functions.py
libreria_experimental-0.2.11.dist-info/METADATA
libreria_experimental-0.2.11.dist-info/WHEEL
libreria_experimental-0.2.11.dist-info/top_level.txt
libreria_experimental-0.2.11.dist-info/RECORD
